controlsim/__init__.py
controlsim-0.1.0.dist-info/licenses/LICENSE
controlsim-0.1.0.dist-info/METADATA
controlsim-0.1.0.dist-info/WHEEL
controlsim-0.1.0.dist-info/top_level.txt
controlsim-0.1.0.dist-info/RECORD
