Metadata-Version: 2.4
Name: controlSim
Version: 0.1.0
Summary: Delay Control System Simulation with PID Controller
Author-email: "Dr. Bharat Verma" <bharat.verma@lnmiit.ac.in>
License: MIT
Project-URL: Homepage, https://github.com/vkbharatv/controlSim
Project-URL: Documentation, https://github.com/vkbharatv/controlSim
Project-URL: Repository, https://github.com/vkbharatv/controlSim.git
Project-URL: Bug Tracker, https://github.com/vkbharatv/controlSim/issues
Keywords: control,simulation,PID,transfer function,delay,IIMC
Classifier: Development Status :: 3 - Alpha
Classifier: Intended Audience :: Science/Research
Classifier: Intended Audience :: Developers
Classifier: License :: OSI Approved :: MIT License
Classifier: Programming Language :: Python :: 3
Classifier: Programming Language :: Python :: 3.8
Classifier: Programming Language :: Python :: 3.9
Classifier: Programming Language :: Python :: 3.10
Classifier: Programming Language :: Python :: 3.11
Classifier: Programming Language :: Python :: 3.12
Classifier: Topic :: Scientific/Engineering
Requires-Python: >=3.8
License-File: LICENSE
Requires-Dist: control>=0.9.4
Requires-Dist: numpy>=1.20.0
Requires-Dist: scipy>=1.7.0
Requires-Dist: matplotlib>=3.3.0
Provides-Extra: dev
Requires-Dist: pytest>=7.0; extra == "dev"
Requires-Dist: pytest-cov>=4.0; extra == "dev"
Requires-Dist: black>=23.0; extra == "dev"
Requires-Dist: flake8>=6.0; extra == "dev"
Requires-Dist: mypy>=1.0; extra == "dev"
Dynamic: license-file
